training/__init__.py
training/client.py
training/model.py
training/resource_pb2.py
training/training_pb2.py
training/training_pb2_grpc.py
training_sdk-0.0.5.dist-info/METADATA
training_sdk-0.0.5.dist-info/WHEEL
training_sdk-0.0.5.dist-info/top_level.txt
training_sdk-0.0.5.dist-info/RECORD
